dimarray/__init__.py
dimarray/_version.py
dimarray/config.py
dimarray/dataset.py
dimarray/plotting.py
dimarray/prettyprinting.py
dimarray/testing.py
dimarray/tools.py
dimarray/compat/__init__.py
dimarray/compat/pycompat.py
dimarray/convert/__init__.py
dimarray/core/__init__.py
dimarray/core/align.py
dimarray/core/axes.py
dimarray/core/bases.py
dimarray/core/dimarraycls.py
dimarray/core/indexing.py
dimarray/core/missingvalues.py
dimarray/core/operation.py
dimarray/core/reshape.py
dimarray/core/transform.py
dimarray/datasets/__init__.py
dimarray/datasets/add_metadata.py
dimarray/datasets/data/cmip5.CSIRO-Mk3-6-0.nc
dimarray/datasets/data/cmip5.GFDL-ESM2G.nc
dimarray/datasets/data/cmip5.HadGEM2-ES.nc
dimarray/datasets/data/cmip5.IPSL-CM5A-LR.nc
dimarray/datasets/data/cmip5.IPSL-CM5A-MR.nc
dimarray/datasets/data/cmip5.MIROC5.nc
dimarray/datasets/data/cmip5.MPI-ESM-MR.nc
dimarray/datasets/data/greenland_velocity.nc
dimarray/datasets/data/polyfits_greenland.dat
dimarray/io/__init__.py
dimarray/io/conventions.py
dimarray/io/nc.py
dimarray/lib/__init__.py
dimarray/lib/stats.py
dimarray/lib/transform.py
dimarray-1.2.1.dist-info/LICENSE
dimarray-1.2.1.dist-info/METADATA
dimarray-1.2.1.dist-info/WHEEL
dimarray-1.2.1.dist-info/top_level.txt
dimarray-1.2.1.dist-info/RECORD
