Metadata-Version: 2.1
Name: dimarray
Version: 1.2.1
Summary: numpy array with labelled dimensions and axes, dimension, NaN handling and netCDF I/O
Author-email: Mahé Perrette <mahe.perrette@gmail.com>
License: BSD-3-Clause
Project-URL: homepage, https://github.com/perrette/dimarray
Project-URL: documentation, https://dimarray.readthedocs.io
Keywords: labelled array,numpy,larry,pandas
Classifier: Programming Language :: Python :: 3
Requires-Python: >=3.7
License-File: LICENSE
Requires-Dist: numpy (>=1.7)
Provides-Extra: ecosystem
Requires-Dist: pandas ; extra == 'ecosystem'
Provides-Extra: netcdf
Requires-Dist: netCDF4 ; extra == 'netcdf'
Provides-Extra: plot
Requires-Dist: matplotlib ; extra == 'plot'
